[
    {
        "nid": "4_1",
        "name": "Chapter 4: Storming the Castle!",
        "tilemap": "Chapter 3_2",
        "bg_tilemap": "Chapter 3",
        "party": "MC",
        "music": {
            "player_phase": "corridorFight",
            "enemy_phase": "corridorFight"
        },
        "objective": {
            "simple": "Get to Throne Room in {eval:game.turncount}/20 turns",
            "win": "Get to Throne Room in {eval:game.turncount}/20 turns",
            "loss": "MC Dies"
        },
        "roam": false,
        "roam_unit": null,
        "go_to_overworld": false,
        "should_record": true,
        "units": [
            {
                "nid": "MC",
                "team": "player",
                "ai": "None",
                "roam_ai": null,
                "ai_group": "",
                "starting_position": null,
                "starting_traveler": null,
                "generic": false
            },
            {
                "nid": "Schuri",
                "team": "player",
                "ai": "None",
                "roam_ai": null,
                "ai_group": "",
                "starting_position": null,
                "starting_traveler": null,
                "generic": false
            },
            {
                "nid": "Senya",
                "team": "player",
                "ai": "None",
                "roam_ai": null,
                "ai_group": "",
                "starting_position": null,
                "starting_traveler": null,
                "generic": false
            },
            {
                "nid": "Lyon",
                "team": "enemy",
                "ai": "Attack",
                "roam_ai": null,
                "ai_group": "",
                "starting_position": null,
                "starting_traveler": null,
                "generic": false
            },
            {
                "nid": "Wall1",
                "variant": null,
                "level": 1,
                "klass": "Wall25",
                "faction": "Wall",
                "starting_items": [],
                "starting_skills": [],
                "team": "enemy",
                "ai": "None",
                "roam_ai": null,
                "ai_group": "",
                "starting_position": [
                    17,
                    9
                ],
                "starting_traveler": null,
                "generic": true
            },
            {
                "nid": "Wall2",
                "variant": null,
                "level": 1,
                "klass": "Wall25",
                "faction": "Wall",
                "starting_items": [],
                "starting_skills": [],
                "team": "enemy",
                "ai": "None",
                "roam_ai": null,
                "ai_group": "",
                "starting_position": [
                    17,
                    12
                ],
                "starting_traveler": null,
                "generic": true
            },
            {
                "nid": "Wall3",
                "variant": null,
                "level": 1,
                "klass": "Wall25",
                "faction": "Wall",
                "starting_items": [],
                "starting_skills": [],
                "team": "enemy",
                "ai": "None",
                "roam_ai": null,
                "ai_group": "",
                "starting_position": [
                    21,
                    8
                ],
                "starting_traveler": null,
                "generic": true
            },
            {
                "nid": "Mentor",
                "team": "enemy",
                "ai": "Pursue",
                "roam_ai": null,
                "ai_group": "",
                "starting_position": null,
                "starting_traveler": null,
                "generic": false
            },
            {
                "nid": "boss",
                "variant": null,
                "level": 11,
                "klass": "Entombed",
                "faction": "Monster",
                "starting_items": [
                    [
                        "Poison Sword",
                        false
                    ]
                ],
                "starting_skills": [
                    "Berserk"
                ],
                "team": "enemy",
                "ai": "Guard",
                "roam_ai": null,
                "ai_group": "",
                "starting_position": null,
                "starting_traveler": null,
                "generic": true
            },
            {
                "nid": "eliteEnemy1",
                "variant": null,
                "level": 9,
                "klass": "Revenant",
                "faction": "Monster",
                "starting_items": [
                    [
                        "Rotten Claw",
                        false
                    ]
                ],
                "starting_skills": [],
                "team": "enemy",
                "ai": "Attack",
                "roam_ai": null,
                "ai_group": "",
                "starting_position": null,
                "starting_traveler": null,
                "generic": true
            },
            {
                "nid": "eliteEnemy2",
                "variant": null,
                "level": 9,
                "klass": "Revenant",
                "faction": "Monster",
                "starting_items": [
                    [
                        "Rotten Claw",
                        false
                    ]
                ],
                "starting_skills": [],
                "team": "enemy",
                "ai": "Attack",
                "roam_ai": null,
                "ai_group": "",
                "starting_position": null,
                "starting_traveler": null,
                "generic": true
            },
            {
                "nid": "mob1",
                "variant": null,
                "level": 7,
                "klass": "Sword_Wight",
                "faction": "Monster",
                "starting_items": [
                    [
                        "Steel Blade",
                        false
                    ]
                ],
                "starting_skills": [],
                "team": "enemy",
                "ai": "Attack",
                "roam_ai": null,
                "ai_group": "",
                "starting_position": null,
                "starting_traveler": null,
                "generic": true
            },
            {
                "nid": "mob2",
                "variant": null,
                "level": 7,
                "klass": "Sword_Wight",
                "faction": "Monster",
                "starting_items": [
                    [
                        "Steel Blade",
                        false
                    ]
                ],
                "starting_skills": [],
                "team": "enemy",
                "ai": "Attack",
                "roam_ai": null,
                "ai_group": "",
                "starting_position": null,
                "starting_traveler": null,
                "generic": true
            },
            {
                "nid": "mob3",
                "variant": null,
                "level": 7,
                "klass": "Sword_Wight",
                "faction": "Monster",
                "starting_items": [
                    [
                        "Steel Blade",
                        false
                    ]
                ],
                "starting_skills": [],
                "team": "enemy",
                "ai": "Attack",
                "roam_ai": null,
                "ai_group": "",
                "starting_position": null,
                "starting_traveler": null,
                "generic": true
            },
            {
                "nid": "mob4",
                "variant": null,
                "level": 7,
                "klass": "Sword_Wight",
                "faction": "Monster",
                "starting_items": [
                    [
                        "Steel Blade",
                        false
                    ]
                ],
                "starting_skills": [],
                "team": "enemy",
                "ai": "Attack",
                "roam_ai": null,
                "ai_group": "",
                "starting_position": null,
                "starting_traveler": null,
                "generic": true
            },
            {
                "nid": "mob5",
                "variant": null,
                "level": 7,
                "klass": "Sword_Bonewalker",
                "faction": "Monster",
                "starting_items": [
                    [
                        "Silver Lance",
                        false
                    ]
                ],
                "starting_skills": [],
                "team": "enemy",
                "ai": "Attack",
                "roam_ai": null,
                "ai_group": "",
                "starting_position": null,
                "starting_traveler": null,
                "generic": true
            },
            {
                "nid": "mob6",
                "variant": null,
                "level": 7,
                "klass": "Bow_Bonewalker",
                "faction": "Monster",
                "starting_items": [
                    [
                        "Silver Bow",
                        false
                    ]
                ],
                "starting_skills": [],
                "team": "enemy",
                "ai": "Attack",
                "roam_ai": null,
                "ai_group": "",
                "starting_position": null,
                "starting_traveler": null,
                "generic": true
            },
            {
                "nid": "mob7",
                "variant": null,
                "level": 8,
                "klass": "Bow_Bonewalker",
                "faction": "Monster",
                "starting_items": [
                    [
                        "Steel Bow",
                        false
                    ]
                ],
                "starting_skills": [],
                "team": "enemy",
                "ai": "Attack",
                "roam_ai": null,
                "ai_group": "",
                "starting_position": null,
                "starting_traveler": null,
                "generic": true
            },
            {
                "nid": "mob8",
                "variant": null,
                "level": 8,
                "klass": "Bow_Bonewalker",
                "faction": "Monster",
                "starting_items": [
                    [
                        "Steel Bow",
                        false
                    ]
                ],
                "starting_skills": [],
                "team": "enemy",
                "ai": "Attack",
                "roam_ai": null,
                "ai_group": "",
                "starting_position": null,
                "starting_traveler": null,
                "generic": true
            },
            {
                "nid": "mob9",
                "variant": null,
                "level": 8,
                "klass": "Bow_Bonewalker",
                "faction": "Monster",
                "starting_items": [
                    [
                        "Steel Bow",
                        false
                    ]
                ],
                "starting_skills": [],
                "team": "enemy",
                "ai": "Attack",
                "roam_ai": null,
                "ai_group": "",
                "starting_position": null,
                "starting_traveler": null,
                "generic": true
            },
            {
                "nid": "mob10",
                "variant": null,
                "level": 7,
                "klass": "Sword_Wight",
                "faction": "Monster",
                "starting_items": [
                    [
                        "Steel Blade",
                        false
                    ]
                ],
                "starting_skills": [],
                "team": "enemy",
                "ai": "Attack",
                "roam_ai": null,
                "ai_group": "",
                "starting_position": null,
                "starting_traveler": null,
                "generic": true
            },
            {
                "nid": "mob11",
                "variant": null,
                "level": 7,
                "klass": "Sword_Wight",
                "faction": "Monster",
                "starting_items": [
                    [
                        "Steel Blade",
                        false
                    ]
                ],
                "starting_skills": [],
                "team": "enemy",
                "ai": "Attack",
                "roam_ai": null,
                "ai_group": "",
                "starting_position": null,
                "starting_traveler": null,
                "generic": true
            },
            {
                "nid": "mob12",
                "variant": null,
                "level": 7,
                "klass": "Sword_Wight",
                "faction": "Monster",
                "starting_items": [
                    [
                        "Steel Blade",
                        false
                    ]
                ],
                "starting_skills": [],
                "team": "enemy",
                "ai": "Attack",
                "roam_ai": null,
                "ai_group": "",
                "starting_position": null,
                "starting_traveler": null,
                "generic": true
            },
            {
                "nid": "mob13",
                "variant": null,
                "level": 7,
                "klass": "Sword_Wight",
                "faction": "Monster",
                "starting_items": [
                    [
                        "Steel Blade",
                        false
                    ]
                ],
                "starting_skills": [],
                "team": "enemy",
                "ai": "Attack",
                "roam_ai": null,
                "ai_group": "",
                "starting_position": null,
                "starting_traveler": null,
                "generic": true
            },
            {
                "nid": "mob14",
                "variant": null,
                "level": 7,
                "klass": "Sword_Wight",
                "faction": "Monster",
                "starting_items": [
                    [
                        "Steel Blade",
                        false
                    ]
                ],
                "starting_skills": [],
                "team": "enemy",
                "ai": "Attack",
                "roam_ai": null,
                "ai_group": "",
                "starting_position": null,
                "starting_traveler": null,
                "generic": true
            },
            {
                "nid": "mob15",
                "variant": null,
                "level": 7,
                "klass": "Sword_Wight",
                "faction": "Monster",
                "starting_items": [
                    [
                        "Steel Blade",
                        false
                    ]
                ],
                "starting_skills": [],
                "team": "enemy",
                "ai": "Attack",
                "roam_ai": null,
                "ai_group": "",
                "starting_position": null,
                "starting_traveler": null,
                "generic": true
            },
            {
                "nid": "mob16",
                "variant": null,
                "level": 7,
                "klass": "Sword_Wight",
                "faction": "Monster",
                "starting_items": [
                    [
                        "Steel Blade",
                        false
                    ]
                ],
                "starting_skills": [],
                "team": "enemy",
                "ai": "Attack",
                "roam_ai": null,
                "ai_group": "",
                "starting_position": null,
                "starting_traveler": null,
                "generic": true
            },
            {
                "nid": "mob17",
                "variant": null,
                "level": 8,
                "klass": "Sword_Bonewalker",
                "faction": "Monster",
                "starting_items": [
                    [
                        "Steel Blade",
                        false
                    ]
                ],
                "starting_skills": [],
                "team": "enemy",
                "ai": "Attack",
                "roam_ai": null,
                "ai_group": "",
                "starting_position": null,
                "starting_traveler": null,
                "generic": true
            },
            {
                "nid": "mob18",
                "variant": null,
                "level": 8,
                "klass": "Sword_Bonewalker",
                "faction": "Monster",
                "starting_items": [
                    [
                        "Steel Blade",
                        false
                    ]
                ],
                "starting_skills": [],
                "team": "enemy",
                "ai": "Attack",
                "roam_ai": null,
                "ai_group": "",
                "starting_position": null,
                "starting_traveler": null,
                "generic": true
            },
            {
                "nid": "mob19",
                "variant": null,
                "level": 8,
                "klass": "Bow_Wight",
                "faction": "Monster",
                "starting_items": [
                    [
                        "Silver Bow",
                        false
                    ]
                ],
                "starting_skills": [],
                "team": "enemy",
                "ai": "Attack",
                "roam_ai": null,
                "ai_group": "",
                "starting_position": null,
                "starting_traveler": null,
                "generic": true
            },
            {
                "nid": "gateGuard",
                "variant": null,
                "level": 9,
                "klass": "Knight",
                "faction": "Monster",
                "starting_items": [
                    [
                        "Silver Lance",
                        false
                    ],
                    [
                        "Door Key",
                        true
                    ]
                ],
                "starting_skills": [],
                "team": "enemy",
                "ai": "AttackTile",
                "roam_ai": null,
                "ai_group": "",
                "starting_position": null,
                "starting_traveler": null,
                "generic": true
            }
        ],
        "regions": [
            {
                "nid": "throneRoom",
                "region_type": "event",
                "position": [
                    26,
                    1
                ],
                "size": [
                    10,
                    4
                ],
                "sub_nid": "Enter",
                "condition": "True",
                "time_left": null,
                "only_once": true,
                "interrupt_move": false
            },
            {
                "nid": "door1",
                "region_type": "event",
                "position": [
                    15,
                    2
                ],
                "size": [
                    1,
                    3
                ],
                "sub_nid": "Open",
                "condition": "True",
                "time_left": null,
                "only_once": false,
                "interrupt_move": false
            },
            {
                "nid": "door2",
                "region_type": "event",
                "position": [
                    19,
                    9
                ],
                "size": [
                    1,
                    3
                ],
                "sub_nid": "Open",
                "condition": "True",
                "time_left": null,
                "only_once": false,
                "interrupt_move": false
            },
            {
                "nid": "door3",
                "region_type": "event",
                "position": [
                    23,
                    4
                ],
                "size": [
                    1,
                    3
                ],
                "sub_nid": "Open",
                "condition": "True",
                "time_left": null,
                "only_once": false,
                "interrupt_move": false
            },
            {
                "nid": "chest1",
                "region_type": "event",
                "position": [
                    19,
                    12
                ],
                "size": [
                    1,
                    1
                ],
                "sub_nid": "Open",
                "condition": "True",
                "time_left": null,
                "only_once": false,
                "interrupt_move": false
            },
            {
                "nid": "chest2",
                "region_type": "event",
                "position": [
                    19,
                    3
                ],
                "size": [
                    1,
                    1
                ],
                "sub_nid": "Open",
                "condition": "True",
                "time_left": null,
                "only_once": false,
                "interrupt_move": false
            },
            {
                "nid": "chest3",
                "region_type": "event",
                "position": [
                    21,
                    3
                ],
                "size": [
                    1,
                    1
                ],
                "sub_nid": "Open",
                "condition": "True",
                "time_left": null,
                "only_once": false,
                "interrupt_move": false
            },
            {
                "nid": "chest4",
                "region_type": "event",
                "position": [
                    23,
                    3
                ],
                "size": [
                    1,
                    1
                ],
                "sub_nid": "Open",
                "condition": "True",
                "time_left": null,
                "only_once": false,
                "interrupt_move": false
            },
            {
                "nid": "mentorArea",
                "region_type": "normal",
                "position": [
                    13,
                    1
                ],
                "size": [
                    6,
                    13
                ],
                "sub_nid": "",
                "condition": "True",
                "time_left": null,
                "only_once": false,
                "interrupt_move": false
            },
            {
                "nid": "wave3Enemies",
                "region_type": "normal",
                "position": [
                    18,
                    1
                ],
                "size": [
                    7,
                    12
                ],
                "sub_nid": "",
                "condition": "True",
                "time_left": null,
                "only_once": false,
                "interrupt_move": false
            },
            {
                "nid": "Door",
                "region_type": "event",
                "position": [
                    15,
                    14
                ],
                "size": [
                    2,
                    2
                ],
                "sub_nid": "Unlock",
                "condition": "unit.can_unlock(region)",
                "time_left": null,
                "only_once": true,
                "interrupt_move": false
            }
        ],
        "unit_groups": [
            {
                "nid": "Party",
                "units": [
                    "Schuri",
                    "Senya",
                    "MC"
                ],
                "positions": {
                    "Schuri": [
                        11,
                        16
                    ],
                    "Senya": [
                        10,
                        16
                    ],
                    "MC": [
                        10,
                        17
                    ]
                }
            },
            {
                "nid": "initialEnemies",
                "units": [
                    "boss",
                    "eliteEnemy1",
                    "eliteEnemy2",
                    "mob1",
                    "mob2",
                    "mob3",
                    "mob4",
                    "mob5",
                    "mob6",
                    "mob7",
                    "mob8",
                    "mob9",
                    "mob10",
                    "mob11",
                    "gateGuard"
                ],
                "positions": {
                    "eliteEnemy1": [
                        20,
                        2
                    ],
                    "eliteEnemy2": [
                        20,
                        11
                    ],
                    "boss": [
                        23,
                        2
                    ],
                    "mob1": [
                        4,
                        10
                    ],
                    "mob2": [
                        5,
                        8
                    ],
                    "mob3": [
                        0,
                        11
                    ],
                    "mob4": [
                        1,
                        5
                    ],
                    "mob5": [
                        2,
                        4
                    ],
                    "mob6": [
                        1,
                        2
                    ],
                    "mob7": [
                        10,
                        1
                    ],
                    "mob8": [
                        9,
                        4
                    ],
                    "mob9": [
                        11,
                        4
                    ],
                    "mob10": [
                        16,
                        8
                    ],
                    "mob11": [
                        14,
                        9
                    ],
                    "gateGuard": [
                        17,
                        15
                    ]
                }
            },
            {
                "nid": "wave2",
                "units": [
                    "mob12",
                    "mob13",
                    "mob14",
                    "mob15",
                    "mob16"
                ],
                "positions": {
                    "mob12": [
                        1,
                        3
                    ],
                    "mob13": [
                        0,
                        4
                    ],
                    "mob14": [
                        1,
                        6
                    ],
                    "mob15": [
                        8,
                        12
                    ],
                    "mob16": [
                        12,
                        10
                    ]
                }
            },
            {
                "nid": "wave3",
                "units": [
                    "mob17",
                    "mob18",
                    "mob19",
                    "Lyon"
                ],
                "positions": {
                    "mob17": [
                        5,
                        5
                    ],
                    "mob18": [
                        5,
                        5
                    ],
                    "mob19": [
                        5,
                        5
                    ],
                    "Lyon": [
                        27,
                        4
                    ]
                }
            }
        ],
        "ai_groups": []
    }
]